aimer/__init__.py
aimer/cli.py
aimer/prompts.py
aimer/ai_providers/__init__.py
aimer/ai_providers/anthropic.py
aimer/ai_providers/anthropic_tool_definitions.txt
aimer/ai_providers/base.py
aimer/ai_providers/open_ai.py
aimer/ai_providers/open_ai_tool_definitions.json
aimer/executor/__init__.py
aimer-0.1.1.dist-info/entry_points.txt
aimer-0.1.1.dist-info/LICENSE
aimer-0.1.1.dist-info/WHEEL
aimer-0.1.1.dist-info/METADATA
aimer-0.1.1.dist-info/RECORD
